kettlebells/__init__.py
kettlebells/__main__.py
kettlebells/console.py
kettlebells/constants.py
kettlebells/database.py
kettlebells/stats.py
kettlebells/workouts.py
kettlebells-0.2.45.dist-info/METADATA
kettlebells-0.2.45.dist-info/WHEEL
kettlebells-0.2.45.dist-info/entry_points.txt
kettlebells-0.2.45.dist-info/licenses/LICENSE
kettlebells-0.2.45.dist-info/RECORD
