Metadata-Version: 2.4
Name: kettlebells
Version: 0.2.45
Summary: A CLI tool to create, save, and track progress of kettlebell workouts.
Author-email: Russell Helmstedter <rhelmstedter@gmail.com>
License-File: LICENSE
Keywords: CLI,fitness,kettlebells
Requires-Python: >=3.12
Requires-Dist: iterfzf>=1.0.0.42.0
Requires-Dist: pandas>=2.1.3
Requires-Dist: plotext>=5.2.8
Requires-Dist: pydantic>=2.5.2
Requires-Dist: pytest-mock>=3.12.0
Requires-Dist: rich>=13.5.2
Requires-Dist: trogon>=0.5.0
Requires-Dist: typer>=0.9.0
Provides-Extra: dev
Requires-Dist: coverage>=7.3.1; extra == 'dev'
Requires-Dist: pytest-cov>=4.1.0; extra == 'dev'
Requires-Dist: pytest>=7.4.0; extra == 'dev'
Requires-Dist: ruff-lsp>=0.0.58; extra == 'dev'
